yatbaf_menu/__init__.py
yatbaf_menu/button.py
yatbaf_menu/filter.py
yatbaf_menu/menu.py
yatbaf_menu/middleware.py
yatbaf_menu/nav.py
yatbaf_menu/payload.py
yatbaf_menu/py.typed
yatbaf_menu/row.py
yatbaf_menu/typing.py
yatbaf_menu/utils.py
yatbaf_menu/version.py
yatbaf_menu-0.5.0.dist-info/METADATA
yatbaf_menu-0.5.0.dist-info/WHEEL
yatbaf_menu-0.5.0.dist-info/licenses/LICENSE
yatbaf_menu-0.5.0.dist-info/RECORD
