Metadata-Version: 2.3
Name: yatbaf-menu
Version: 0.5.0
Summary: Inline menu builder for yatbaf
Project-URL: Source, https://codeberg.org/maraudeur/yatbaf-menu
Author-email: Maraudeur <maraudeur1@protonmail.ch>
License:  The MIT License (MIT)
License-File: LICENSE
Keywords: telegram-bot,telegram-bot-api,yatbaf
Classifier: Development Status :: 4 - Beta
Classifier: Intended Audience :: Developers
Classifier: License :: OSI Approved :: MIT License
Classifier: Programming Language :: Python
Classifier: Programming Language :: Python :: 3
Classifier: Programming Language :: Python :: 3.11
Classifier: Programming Language :: Python :: 3.12
Classifier: Typing :: Typed
Requires-Python: >=3.11
Requires-Dist: yatbaf>=0.11.0
Provides-Extra: dev
Requires-Dist: pre-commit<4.0.0,>=3.0.0; extra == 'dev'
Provides-Extra: lint
Requires-Dist: flake8-bugbear==23.3.23; extra == 'lint'
Requires-Dist: flake8-unused-arguments==0.0.13; extra == 'lint'
Requires-Dist: flake8==6.0.0; extra == 'lint'
Requires-Dist: isort<6.0.0,>=5.10.0; extra == 'lint'
Requires-Dist: mypy==1.9.0; extra == 'lint'
Requires-Dist: yapf==0.40.1; extra == 'lint'
Provides-Extra: test
Requires-Dist: coverage==7.1.0; extra == 'test'
Requires-Dist: pytest-asyncio==0.21.0; extra == 'test'
Requires-Dist: pytest-cov==4.0.0; extra == 'test'
Requires-Dist: pytest>=7.0.0; extra == 'test'
